{
  "version": "v1.0.0",
  "project": {
    "name": "layercake"
  },
  "localPath": "./build",
  "debug": {
    "remotePath": "/ruhnn/web/tradeCenter/resource/test",
    "server": {
      "host": "116.62.181.135",
      "port": 22,
      "user": "root",
      "password": "Ruhnn1818"
    }
  },
  "test": {
    "remotePath": "/ruhnn/web",
    "server": {
      "host": "192.168.10.249",
      "port": 21,
      "user": "admin",
      "password": "123456"
    }
  },
  "prod": {
    "remotePath": "/ruhnn/web",
    "server": {
      "host": "116.62.181.135",
      "port": 22,
      "user": "root",
      "password": "Ruhnn1818"
    }
  }
}